Metadata-Version: 2.1
Name: jk-pypi
Version: 0.2019.9.12
Summary: This python module allows retrieving data from pypi.org.
Home-page: https://github.com/jkpubsrc/python-module-jk-pypi
Author: Jürgen Knauth
Author-email: pubsrc@binary-overflow.de
License: Apache 2.0
Download-URL: https://github.com/jkpubsrc/python-module-jk-pypi/tarball/0.2019.9.12
Keywords: pypi
Platform: UNKNOWN
Classifier: Programming Language :: Python :: 3
Classifier: Development Status :: 5 - Production/Stable
Classifier: License :: OSI Approved :: Apache Software License
